<?xml version="1.0" encoding="utf-8"?>
<odoo>
    <record id="loyalty_program_view_form" model="ir.ui.view">
        <field name="name">loyalty.program.view.form</field>
        <field name="model">loyalty.program</field>
        <field name="inherit_id" ref="loyalty.loyalty_program_view_form"/>
        <field name="arch" type="xml">
            <field name="date_to" position="after">
                 <field name="sale_domain" string="Sales domain" widget="domain" options="{'model': 'sale.order', 'in_dialog': true}"/>
            </field>
        </field>
    </record>
</odoo>
